{
  "lastUpdated": "2026-07-11T08:29:01.773Z",
  "pathway": {
    "name": "Modern React Engineer",
    "version": "1.0.0",
    "overallScore": 59.8,
    "completionPercentage": 62.3,
    "badgeLevel": "none",
    "totalChallenges": 53,
    "completedChallenges": 33
  },
  "courses": {
    "01-react-fundamentals": {
      "courseId": "01-react-fundamentals",
      "courseName": "React Fundamentals",
      "averageScore": 93.2,
      "completionPercentage": 100,
      "badgeLevel": "gold",
      "totalChallenges": 23,
      "completedChallenges": 23,
      "challenges": {
        "01-static-task-display": {
          "challengeId": "01-static-task-display",
          "challengeName": "Static Task Display",
          "passed": true,
          "score": 90.855,
          "lastRun": "2026-06-10T07:35:17.222Z",
          "scores": {
            "functionalTests": 83.3,
            "codeQuality": 90,
            "architecture": 100,
            "bestPractices": 100,
            "e2eTests": 100,
            "aiReview": 88
          }
        },
        "02-dynamic-task-rendering": {
          "challengeId": "02-dynamic-task-rendering",
          "challengeName": "Dynamic Task Rendering",
          "passed": true,
          "score": 89.45,
          "lastRun": "2026-06-10T08:30:44.095Z",
          "scores": {
            "functionalTests": 75,
            "codeQuality": 100,
            "architecture": 100,
            "bestPractices": 100,
            "e2eTests": 100,
            "aiReview": 88
          }
        },
        "03-adding-new-tasks": {
          "challengeId": "03-adding-new-tasks",
          "challengeName": "Adding New Tasks",
          "passed": true,
          "score": 92.355,
          "lastRun": "2026-06-10T18:00:23.258Z",
          "scores": {
            "functionalTests": 83.3,
            "codeQuality": 100,
            "architecture": 100,
            "bestPractices": 100,
            "e2eTests": 100,
            "aiReview": 88
          }
        },
        "04-task-completion-toggle": {
          "challengeId": "04-task-completion-toggle",
          "challengeName": "Task Completion Toggle",
          "passed": true,
          "score": 84.7,
          "lastRun": "2026-06-14T08:01:45.012Z",
          "scores": {
            "functionalTests": 100,
            "codeQuality": 90,
            "architecture": 100,
            "bestPractices": 100,
            "e2eTests": 25,
            "aiReview": 83
          }
        },
        "05-task-deletion": {
          "challengeId": "05-task-deletion",
          "challengeName": "Task Deletion",
          "passed": true,
          "score": 86.545,
          "lastRun": "2026-06-16T05:49:26.025Z",
          "scores": {
            "functionalTests": 66.7,
            "codeQuality": 100,
            "architecture": 100,
            "bestPractices": 100,
            "e2eTests": 100,
            "aiReview": 88
          }
        },
        "06-task-filtering": {
          "challengeId": "06-task-filtering",
          "challengeName": "Task Filtering",
          "passed": true,
          "score": 98.2,
          "lastRun": "2026-06-16T06:20:48.658Z",
          "scores": {
            "functionalTests": 100,
            "codeQuality": 100,
            "architecture": 100,
            "bestPractices": 100,
            "e2eTests": 100,
            "aiReview": 88
          }
        },
        "07-priority-based-sorting": {
          "challengeId": "07-priority-based-sorting",
          "challengeName": "Priority-Based Sorting",
          "passed": true,
          "score": 98.2,
          "lastRun": "2026-06-16T06:25:32.334Z",
          "scores": {
            "functionalTests": 100,
            "codeQuality": 100,
            "architecture": 100,
            "bestPractices": 100,
            "e2eTests": 100,
            "aiReview": 88
          }
        },
        "08-task-editing": {
          "challengeId": "08-task-editing",
          "challengeName": "Task Editing",
          "passed": true,
          "score": 98.2,
          "lastRun": "2026-06-16T07:36:45.378Z",
          "scores": {
            "functionalTests": 100,
            "codeQuality": 100,
            "architecture": 100,
            "bestPractices": 100,
            "e2eTests": 100,
            "aiReview": 88
          }
        },
        "09-search-functionality": {
          "challengeId": "09-search-functionality",
          "challengeName": "Search Functionality",
          "passed": true,
          "score": 90.7,
          "lastRun": "2026-06-16T07:45:13.855Z",
          "scores": {
            "functionalTests": 100,
            "codeQuality": 100,
            "architecture": 100,
            "bestPractices": 100,
            "e2eTests": 50,
            "aiReview": 88
          }
        },
        "10-useeffect-local-storage": {
          "challengeId": "10-useeffect-local-storage",
          "challengeName": "useEffect - Local Storage Persistence",
          "passed": true,
          "score": 98.2,
          "lastRun": "2026-06-16T07:50:21.533Z",
          "scores": {
            "functionalTests": 100,
            "codeQuality": 100,
            "architecture": 100,
            "bestPractices": 100,
            "e2eTests": 100,
            "aiReview": 88
          }
        },
        "11-useeffect-debounced-search": {
          "challengeId": "11-useeffect-debounced-search",
          "challengeName": "useEffect - Debounced Search",
          "passed": true,
          "score": 98.2,
          "lastRun": "2026-06-16T08:25:08.366Z",
          "scores": {
            "functionalTests": 100,
            "codeQuality": 100,
            "architecture": 100,
            "bestPractices": 100,
            "e2eTests": 100,
            "aiReview": 88
          }
        },
        "12-categories-and-tags": {
          "challengeId": "12-categories-and-tags",
          "challengeName": "Categories and Tags",
          "passed": true,
          "score": 98.2,
          "lastRun": "2026-06-16T20:46:20.798Z",
          "scores": {
            "functionalTests": 100,
            "codeQuality": 100,
            "architecture": 100,
            "bestPractices": 100,
            "e2eTests": 100,
            "aiReview": 88
          }
        },
        "13-due-dates-and-sorting": {
          "challengeId": "13-due-dates-and-sorting",
          "challengeName": "Due Dates and Sorting",
          "passed": true,
          "score": 97.45,
          "lastRun": "2026-06-20T06:46:37.782Z",
          "scores": {
            "functionalTests": 100,
            "codeQuality": 100,
            "architecture": 100,
            "bestPractices": 100,
            "e2eTests": 100,
            "aiReview": 83
          }
        },
        "14-task-statistics-dashboard": {
          "challengeId": "14-task-statistics-dashboard",
          "challengeName": "Task Statistics Dashboard",
          "passed": true,
          "score": 86.545,
          "lastRun": "2026-06-20T07:56:54.315Z",
          "scores": {
            "functionalTests": 66.7,
            "codeQuality": 100,
            "architecture": 100,
            "bestPractices": 100,
            "e2eTests": 100,
            "aiReview": 88
          }
        },
        "15-component-organization": {
          "challengeId": "15-component-organization",
          "challengeName": "Component Organization with Props",
          "passed": true,
          "score": 98.2,
          "lastRun": "2026-06-20T08:09:36.782Z",
          "scores": {
            "functionalTests": 100,
            "codeQuality": 100,
            "architecture": 100,
            "bestPractices": 100,
            "e2eTests": 100,
            "aiReview": 88
          }
        },
        "16-context-api-theme": {
          "challengeId": "16-context-api-theme",
          "challengeName": "Context API - Theme Management",
          "passed": true,
          "score": 97.60000000000001,
          "lastRun": "2026-06-20T19:50:00.454Z",
          "scores": {
            "functionalTests": 100,
            "codeQuality": 96,
            "architecture": 100,
            "bestPractices": 100,
            "e2eTests": 100,
            "aiReview": 88
          }
        },
        "17-custom-hook-uselocalstorage": {
          "challengeId": "17-custom-hook-uselocalstorage",
          "challengeName": "Custom Hook - useLocalStorage",
          "passed": true,
          "score": 96.10000000000001,
          "lastRun": "2026-06-20T20:00:47.294Z",
          "scores": {
            "functionalTests": 100,
            "codeQuality": 86,
            "architecture": 100,
            "bestPractices": 100,
            "e2eTests": 100,
            "aiReview": 88
          }
        },
        "18-usereducer-complex-state": {
          "challengeId": "18-usereducer-complex-state",
          "challengeName": "useReducer - Complex State Management",
          "passed": true,
          "score": 94.45,
          "lastRun": "2026-06-20T20:53:15.386Z",
          "scores": {
            "functionalTests": 100,
            "codeQuality": 80,
            "architecture": 100,
            "bestPractices": 100,
            "e2eTests": 100,
            "aiReview": 83
          }
        },
        "19-performance-optimization": {
          "challengeId": "19-performance-optimization",
          "challengeName": "Performance Optimization",
          "passed": true,
          "score": 94.45,
          "lastRun": "2026-06-20T21:13:41.994Z",
          "scores": {
            "functionalTests": 100,
            "codeQuality": 80,
            "architecture": 100,
            "bestPractices": 100,
            "e2eTests": 100,
            "aiReview": 83
          }
        },
        "20-error-boundaries": {
          "challengeId": "20-error-boundaries",
          "challengeName": "Error Boundaries and Error Handling",
          "passed": true,
          "score": 81.7,
          "lastRun": "2026-06-20T21:41:23.192Z",
          "scores": {
            "functionalTests": 100,
            "codeQuality": 90,
            "architecture": 100,
            "bestPractices": 100,
            "e2eTests": 0,
            "aiReview": 88
          }
        },
        "21-react-router": {
          "challengeId": "21-react-router",
          "challengeName": "React Router - Routing and Navigation",
          "passed": true,
          "score": 83.5,
          "lastRun": "2026-06-20T22:15:15.092Z",
          "scores": {
            "functionalTests": 100,
            "codeQuality": 90,
            "architecture": 100,
            "bestPractices": 100,
            "e2eTests": 100,
            "aiReview": 0
          }
        },
        "22-data-fetching": {
          "challengeId": "22-data-fetching",
          "challengeName": "Data Fetching - Loading and Error State",
          "passed": true,
          "score": 98.2,
          "lastRun": "2026-06-20T22:18:26.837Z",
          "scores": {
            "functionalTests": 100,
            "codeQuality": 100,
            "architecture": 100,
            "bestPractices": 100,
            "e2eTests": 100,
            "aiReview": 88
          }
        },
        "23-useref-focus-management": {
          "challengeId": "23-useref-focus-management",
          "challengeName": "useRef - Focus Management",
          "passed": true,
          "score": 91.705,
          "lastRun": "2026-06-20T22:27:33.596Z",
          "scores": {
            "functionalTests": 100,
            "codeQuality": 90,
            "architecture": 100,
            "bestPractices": 100,
            "e2eTests": 66.7,
            "aiReview": 88
          }
        }
      }
    },
    "02-redux-rtk-query": {
      "courseId": "02-redux-rtk-query",
      "courseName": "Redux & RTK Query",
      "averageScore": 87.9,
      "completionPercentage": 76.9,
      "badgeLevel": "silver",
      "totalChallenges": 13,
      "completedChallenges": 10,
      "challenges": {
        "01-store-setup": {
          "challengeId": "01-store-setup",
          "challengeName": "Store Setup with configureStore",
          "passed": true,
          "score": 81.67,
          "lastRun": "2026-07-10T17:21:23.093Z",
          "scores": {
            "functionalTests": 100,
            "codeQuality": 100,
            "architecture": 66.7,
            "bestPractices": 100,
            "e2eTests": 100,
            "aiReview": 0
          }
        },
        "02-first-slice": {
          "challengeId": "02-first-slice",
          "challengeName": "First Slice with createSlice",
          "passed": true,
          "score": 92.9,
          "lastRun": "2026-07-10T17:32:56.859Z",
          "scores": {
            "functionalTests": 100,
            "codeQuality": 100,
            "architecture": 50,
            "bestPractices": 100,
            "e2eTests": 100,
            "aiReview": 86
          }
        },
        "03-reading-dispatching": {
          "challengeId": "03-reading-dispatching",
          "challengeName": "Reading and Dispatching in Components",
          "passed": true,
          "score": 82.905,
          "lastRun": "2026-07-10T17:43:52.421Z",
          "scores": {
            "functionalTests": 100,
            "codeQuality": 100,
            "architecture": 0,
            "bestPractices": 100,
            "e2eTests": 66.7,
            "aiReview": 86
          }
        },
        "04-multiple-slices": {
          "challengeId": "04-multiple-slices",
          "challengeName": "Multiple Slices in the Store",
          "passed": true,
          "score": 92.9,
          "lastRun": "2026-07-10T17:59:50.880Z",
          "scores": {
            "functionalTests": 100,
            "codeQuality": 100,
            "architecture": 50,
            "bestPractices": 100,
            "e2eTests": 100,
            "aiReview": 86
          }
        },
        "05-async-thunks": {
          "challengeId": "05-async-thunks",
          "challengeName": "Async Logic with createAsyncThunk",
          "passed": true,
          "score": 91.4,
          "lastRun": "2026-07-11T05:59:23.466Z",
          "scores": {
            "functionalTests": 100,
            "codeQuality": 90,
            "architecture": 50,
            "bestPractices": 100,
            "e2eTests": 100,
            "aiReview": 86
          }
        },
        "06-rtk-query-setup": {
          "challengeId": "06-rtk-query-setup",
          "challengeName": "RTK Query Setup and API Slice",
          "passed": true,
          "score": 85,
          "lastRun": "2026-07-11T06:09:35.405Z",
          "scores": {
            "functionalTests": 100,
            "codeQuality": 100,
            "architecture": 100,
            "bestPractices": 100,
            "e2eTests": 100,
            "aiReview": 0
          }
        },
        "07-queries": {
          "challengeId": "07-queries",
          "challengeName": "Query Endpoints and useQuery Hooks",
          "passed": true,
          "score": 86.85,
          "lastRun": "2026-07-11T06:15:46.513Z",
          "scores": {
            "functionalTests": 100,
            "codeQuality": 100,
            "architecture": 0,
            "bestPractices": 100,
            "e2eTests": 100,
            "aiReview": 79
          }
        },
        "08-caching-refetch": {
          "challengeId": "08-caching-refetch",
          "challengeName": "Caching and Cache Tags",
          "passed": true,
          "score": 82.9,
          "lastRun": "2026-07-11T06:22:29.995Z",
          "scores": {
            "functionalTests": 100,
            "codeQuality": 100,
            "architecture": 100,
            "bestPractices": 100,
            "e2eTests": 0,
            "aiReview": 86
          }
        },
        "09-mutations": {
          "challengeId": "09-mutations",
          "challengeName": "Mutations with useMutation",
          "passed": true,
          "score": 85,
          "lastRun": "2026-07-11T08:22:40.037Z",
          "scores": {
            "functionalTests": 100,
            "codeQuality": 100,
            "architecture": 100,
            "bestPractices": 100,
            "e2eTests": 100,
            "aiReview": 0
          }
        },
        "10-optimistic-updates": {
          "challengeId": "10-optimistic-updates",
          "challengeName": "Optimistic Updates",
          "passed": true,
          "score": 97.9,
          "lastRun": "2026-07-11T08:28:49.662Z",
          "scores": {
            "functionalTests": 100,
            "codeQuality": 100,
            "architecture": 100,
            "bestPractices": 100,
            "e2eTests": 100,
            "aiReview": 86
          }
        }
      }
    },
    "03-nextjs-app-router": {
      "courseId": "03-nextjs-app-router",
      "courseName": "Next.js App Router",
      "averageScore": 0,
      "completionPercentage": 0,
      "badgeLevel": "none",
      "totalChallenges": 17,
      "completedChallenges": 0,
      "challenges": {}
    }
  }
}